{
    "PrescriptionReportBean": [
        {
            "parentClass": "PrescriptionReportBean",
            "name": "PrescriptionReportBean",
            "sourceCode": "public PrescriptionReportBean() {\r\n\t}"
        },
        {
            "parentClass": "PrescriptionReportBean",
            "name": "getPrescription",
            "sourceCode": "public PrescriptionBean getPrescription() {\r\n\t\treturn prescription;\r\n\t}"
        },
        {
            "parentClass": "PrescriptionReportBean",
            "name": "setPrescription",
            "sourceCode": "public void setPrescription(PrescriptionBean prescription) {\r\n\t\tthis.prescription = prescription;\r\n\t}"
        },
        {
            "parentClass": "PrescriptionReportBean",
            "name": "getOfficeVisit",
            "sourceCode": "public OfficeVisitBean getOfficeVisit() {\r\n\t\treturn officeVisit;\r\n\t}"
        },
        {
            "parentClass": "PrescriptionReportBean",
            "name": "setOfficeVisit",
            "sourceCode": "public void setOfficeVisit(OfficeVisitBean officeVisit) {\r\n\t\tthis.officeVisit = officeVisit;\r\n\t}"
        }
    ]
}